Metadata-Version: 1.1
Name: MultiDownloader
Version: 0.1
Summary: A libary to download media from social media like twitter.com, instagram.com, snapchat.com and more will be added with the next updates
Home-page: UNKNOWN
Author: Yazan Talib
Author-email: y1z1n.xx@gmail.com
License: MIT
Keywords: Downloader,Multi downloader,Social media downloader
Platform: UNKNOWN
Classifier: Development Status :: 5 - Production/Stable
Classifier: Intended Audience :: Education
Classifier: Operating System :: Microsoft :: Windows :: Windows 10
Classifier: License :: OSI Approved :: MIT License
Classifier: Programming Language :: Python :: 3
